multidet/__init__.py
multidet/loss.py
multidet/metric.py
multidet/custom/__init__.py
multidet/custom/activation.py
multidet/data/__init__.py
multidet/data/caltech.py
multidet/data/classes.py
multidet/data/genRecordIO.py
multidet/data/image.py
multidet/data/loadimg.py
multidet/model/__init__.py
multidet/model/anchor.py
multidet/model/box.py
multidet/model/box_np.py
multidet/model/coder.py
multidet/model/mobilenet.py
multidet/model/ssd_net.py
multidet/model/vgg_base.py
multidet/utils/__init__.py
multidet/utils/utils.py
multidet-0.1.2.dist-info/LICENSE
multidet-0.1.2.dist-info/METADATA
multidet-0.1.2.dist-info/WHEEL
multidet-0.1.2.dist-info/top_level.txt
multidet-0.1.2.dist-info/RECORD
