Metadata-Version: 2.1
Name: multidet
Version: 0.1.2
Summary: multi detection
Home-page: https://github.com/ydlstartx/MultiDet
Author: startx
Author-email: ydl_startx@163.com
License: UNKNOWN
Platform: UNKNOWN
Classifier: Programming Language :: Python :: 3
Classifier: License :: OSI Approved :: MIT License
Classifier: Operating System :: OS Independent
Requires-Python: >=3.6
